streptofile/Spyogenes_typer.py
streptofile/__init__.py
streptofile/_modidx.py
streptofile/analysis_utility.py
streptofile/convert_external_genome.py
streptofile/core.py
streptofile/hello_world.py
streptofile/sample_manager.py
streptofile/config/config.default.env
streptofile/config/config.default.yaml
streptofile-0.0.1.dist-info/LICENSE
streptofile-0.0.1.dist-info/METADATA
streptofile-0.0.1.dist-info/WHEEL
streptofile-0.0.1.dist-info/entry_points.txt
streptofile-0.0.1.dist-info/top_level.txt
streptofile-0.0.1.dist-info/RECORD
